{
    "asset": {
        "format": "png",
        "id": "671836b2e5d71978a444f17b6ead9d9b",
        "name": "artifact_2_2.png",
        "path": "file:/Users/asherlk1/Documents/MICA/Labanotation/labanotation-pipeline/data/coppelia_dawn/artifact_2_2.png",
        "size": {
            "width": 1014,
            "height": 1806
        },
        "state": 2,
        "type": 1
    },
    "regions": [
        {
            "id": "GTIDZwtF7",
            "type": "RECTANGLE",
            "tags": [
                "left_support_middle",
                "forward"
            ],
            "boundingBox": {
                "height": 272.2517964071856,
                "width": 44.397971082089555,
                "left": 478.6906982942431,
                "top": 19.34758607784431
            },
            "points": [
                {
                    "x": 478.6906982942431,
                    "y": 19.34758607784431
                },
                {
                    "x": 523.0886693763326,
                    "y": 19.34758607784431
                },
                {
                    "x": 523.0886693763326,
                    "y": 291.59938248502993
                },
                {
                    "x": 478.6906982942431,
                    "y": 291.59938248502993
                }
            ]
        },
        {
            "id": "8WT1qW2Lb",
            "type": "RECTANGLE",
            "tags": [
                "forward",
                "left_support_low"
            ],
            "boundingBox": {
                "height": 107.5691991017964,
                "width": 39.592484008528785,
                "left": 479.18053704690834,
                "top": 547.6549681886228
            },
            "points": [
                {
                    "x": 479.18053704690834,
                    "y": 547.6549681886228
                },
                {
                    "x": 518.7730210554371,
                    "y": 547.6549681886228
                },
                {
                    "x": 518.7730210554371,
                    "y": 655.2241672904191
                },
                {
                    "x": 479.18053704690834,
                    "y": 655.2241672904191
                }
            ]
        },
        {
            "id": "CJfVpYIwh",
            "type": "RECTANGLE",
            "tags": [
                "left_support_low",
                "place"
            ],
            "boundingBox": {
                "height": 76.30890718562874,
                "width": 43.45207555970149,
                "left": 474.29904051172707,
                "top": 1358.7074663173653
            },
            "points": [
                {
                    "x": 474.29904051172707,
                    "y": 1358.7074663173653
                },
                {
                    "x": 517.7511160714286,
                    "y": 1358.7074663173653
                },
                {
                    "x": 517.7511160714286,
                    "y": 1435.016373502994
                },
                {
                    "x": 474.29904051172707,
                    "y": 1435.016373502994
                }
            ]
        },
        {
            "id": "hjoZggYuU",
            "type": "RECTANGLE",
            "tags": [
                "left_leg_low",
                "left"
            ],
            "boundingBox": {
                "height": 74.10378929640719,
                "width": 25.99523587420043,
                "left": 423.76119402985074,
                "top": 1557.2103199850299
            },
            "points": [
                {
                    "x": 423.76119402985074,
                    "y": 1557.2103199850299
                },
                {
                    "x": 449.7564299040512,
                    "y": 1557.2103199850299
                },
                {
                    "x": 449.7564299040512,
                    "y": 1631.314109281437
                },
                {
                    "x": 423.76119402985074,
                    "y": 1631.314109281437
                }
            ]
        },
        {
            "id": "GP5d5Mct0",
            "type": "RECTANGLE",
            "tags": [
                "right",
                "left_leg_low"
            ],
            "boundingBox": {
                "height": 56.74165419161676,
                "width": 19.635777585287848,
                "left": 408.6268656716418,
                "top": 1569.89186002994
            },
            "points": [
                {
                    "x": 408.6268656716418,
                    "y": 1569.89186002994
                },
                {
                    "x": 428.26264325692966,
                    "y": 1569.89186002994
                },
                {
                    "x": 428.26264325692966,
                    "y": 1626.6335142215569
                },
                {
                    "x": 408.6268656716418,
                    "y": 1626.6335142215569
                }
            ]
        },
        {
            "id": "nRl85dwqd",
            "type": "RECTANGLE",
            "tags": [
                "left_leg_low",
                "forward"
            ],
            "boundingBox": {
                "height": 133.26177956586827,
                "width": 42.07545975479744,
                "left": 412.4780117270789,
                "top": 692.1789015718563
            },
            "points": [
                {
                    "x": 412.4780117270789,
                    "y": 692.1789015718563
                },
                {
                    "x": 454.55347148187633,
                    "y": 692.1789015718563
                },
                {
                    "x": 454.55347148187633,
                    "y": 825.4406811377245
                },
                {
                    "x": 412.4780117270789,
                    "y": 825.4406811377245
                }
            ]
        },
        {
            "id": "5wIK2TOLH",
            "type": "RECTANGLE",
            "tags": [
                "place",
                "left_leg_low"
            ],
            "boundingBox": {
                "height": 135.77950037425148,
                "width": 44.27128864605544,
                "left": 411.38009728144993,
                "top": 829.0060441616766
            },
            "points": [
                {
                    "x": 411.38009728144993,
                    "y": 829.0060441616766
                },
                {
                    "x": 455.6513859275054,
                    "y": 829.0060441616766
                },
                {
                    "x": 455.6513859275054,
                    "y": 964.7855445359281
                },
                {
                    "x": 411.38009728144993,
                    "y": 964.7855445359281
                }
            ]
        },
        {
            "id": "p9esdCrjE",
            "type": "RECTANGLE",
            "tags": [
                "left_body_low",
                "forward"
            ],
            "boundingBox": {
                "height": 332.5588136227545,
                "width": 43.4605210554371,
                "left": 371.38222947761193,
                "top": 689.7879116766467
            },
            "points": [
                {
                    "x": 371.38222947761193,
                    "y": 689.7879116766467
                },
                {
                    "x": 414.84275053304907,
                    "y": 689.7879116766467
                },
                {
                    "x": 414.84275053304907,
                    "y": 1022.3467252994011
                },
                {
                    "x": 371.38222947761193,
                    "y": 1022.3467252994011
                }
            ]
        },
        {
            "id": "eJI7rsGqm",
            "type": "RECTANGLE",
            "tags": [
                "left",
                "left_arm_high"
            ],
            "boundingBox": {
                "height": 176.18131549401195,
                "width": 39.35601012793177,
                "left": 312.9140625,
                "top": 1429.2965849550897
            },
            "points": [
                {
                    "x": 312.9140625,
                    "y": 1429.2965849550897
                },
                {
                    "x": 352.27007262793177,
                    "y": 1429.2965849550897
                },
                {
                    "x": 352.27007262793177,
                    "y": 1605.4779004491018
                },
                {
                    "x": 312.9140625,
                    "y": 1605.4779004491018
                }
            ]
        },
        {
            "id": "bsvRo62ca",
            "type": "RECTANGLE",
            "tags": [
                "right_support_middle",
                "place"
            ],
            "boundingBox": {
                "height": 146.078499251497,
                "width": 43.7898953891258,
                "left": 512.3037713219617,
                "top": 553.1466410928143
            },
            "points": [
                {
                    "x": 512.3037713219617,
                    "y": 553.1466410928143
                },
                {
                    "x": 556.0936667110874,
                    "y": 553.1466410928143
                },
                {
                    "x": 556.0936667110874,
                    "y": 699.2251403443113
                },
                {
                    "x": 512.3037713219617,
                    "y": 699.2251403443113
                }
            ]
        },
        {
            "id": "UT4p1AWvQ",
            "type": "RECTANGLE",
            "tags": [
                "right_support_low",
                "forward"
            ],
            "boundingBox": {
                "height": 106.88485217065868,
                "width": 44.92159181769723,
                "left": 509.2549473614073,
                "top": 956.9282279191616
            },
            "points": [
                {
                    "x": 509.2549473614073,
                    "y": 956.9282279191616
                },
                {
                    "x": 554.1765391791045,
                    "y": 956.9282279191616
                },
                {
                    "x": 554.1765391791045,
                    "y": 1063.8130800898202
                },
                {
                    "x": 509.2549473614073,
                    "y": 1063.8130800898202
                }
            ]
        },
        {
            "id": "coRDtz1JQ",
            "type": "RECTANGLE",
            "tags": [
                "right_leg_low",
                "forward"
            ],
            "boundingBox": {
                "height": 110.15450973053892,
                "width": 40.58905250533049,
                "left": 576.9033682036247,
                "top": 1292.0639034431138
            },
            "points": [
                {
                    "x": 576.9033682036247,
                    "y": 1292.0639034431138
                },
                {
                    "x": 617.4924207089553,
                    "y": 1292.0639034431138
                },
                {
                    "x": 617.4924207089553,
                    "y": 1402.2184131736526
                },
                {
                    "x": 576.9033682036247,
                    "y": 1402.2184131736526
                }
            ]
        },
        {
            "id": "jJC2PeMba",
            "type": "RECTANGLE",
            "tags": [
                "right_arm_high",
                "forward_diagonal"
            ],
            "boundingBox": {
                "height": 237.69650074850298,
                "width": 44.52465351812367,
                "left": 674.220815565032,
                "top": 829.9523016467066
            },
            "points": [
                {
                    "x": 674.220815565032,
                    "y": 829.9523016467066
                },
                {
                    "x": 718.7454690831556,
                    "y": 829.9523016467066
                },
                {
                    "x": 718.7454690831556,
                    "y": 1067.6488023952095
                },
                {
                    "x": 674.220815565032,
                    "y": 1067.6488023952095
                }
            ]
        },
        {
            "id": "1goXZmBUa",
            "type": "RECTANGLE",
            "tags": [
                "forward_diagonal",
                "left_arm_middle"
            ],
            "boundingBox": {
                "height": 236.50523016467065,
                "width": 49.1781216684435,
                "left": 305.6255996801706,
                "top": 825.6265531437125
            },
            "points": [
                {
                    "x": 305.6255996801706,
                    "y": 825.6265531437125
                },
                {
                    "x": 354.8037213486141,
                    "y": 825.6265531437125
                },
                {
                    "x": 354.8037213486141,
                    "y": 1062.131783308383
                },
                {
                    "x": 305.6255996801706,
                    "y": 1062.131783308383
                }
            ]
        },
        {
            "id": "v99pMgpNc",
            "type": "RECTANGLE",
            "tags": [
                "right_arm_low",
                "forward"
            ],
            "boundingBox": {
                "height": 139.73350486526945,
                "width": 51.1628131663113,
                "left": 667.1857176172708,
                "top": 1430.0738678892214
            },
            "points": [
                {
                    "x": 667.1857176172708,
                    "y": 1430.0738678892214
                },
                {
                    "x": 718.3485307835821,
                    "y": 1430.0738678892214
                },
                {
                    "x": 718.3485307835821,
                    "y": 1569.8073727544909
                },
                {
                    "x": 667.1857176172708,
                    "y": 1569.8073727544909
                }
            ]
        },
        {
            "id": "HMMOEwdWf",
            "type": "RECTANGLE",
            "tags": [
                "measure_7"
            ],
            "boundingBox": {
                "height": 812.7361778846155,
                "width": 1011.7095448369565,
                "left": 2.2904551630434784,
                "top": 826.0875400641027
            },
            "points": [
                {
                    "x": 2.2904551630434784,
                    "y": 826.0875400641027
                },
                {
                    "x": 1014,
                    "y": 826.0875400641027
                },
                {
                    "x": 1014,
                    "y": 1638.823717948718
                },
                {
                    "x": 2.2904551630434784,
                    "y": 1638.823717948718
                }
            ]
        },
        {
            "id": "FCzUlMCvi",
            "type": "RECTANGLE",
            "tags": [
                "measure_8"
            ],
            "boundingBox": {
                "height": 818.128405448718,
                "width": 1006.8530910326086,
                "left": 7.146908967391304,
                "top": 4.341346153846154
            },
            "points": [
                {
                    "x": 7.146908967391304,
                    "y": 4.341346153846154
                },
                {
                    "x": 1014,
                    "y": 4.341346153846154
                },
                {
                    "x": 1014,
                    "y": 822.4697516025642
                },
                {
                    "x": 7.146908967391304,
                    "y": 822.4697516025642
                }
            ]
        }
    ],
    "version": "2.2.0"
}